enf/__init__.py
enf/enf.py
enf-0.0.1.dist-info/LICENSE
enf-0.0.1.dist-info/METADATA
enf-0.0.1.dist-info/WHEEL
enf-0.0.1.dist-info/top_level.txt
enf-0.0.1.dist-info/RECORD
